cryptoprice/__init__.py
cryptoprice/client.py
cryptoprice/errors.py
cryptoprice_blockxai-0.1.1.dist-info/licenses/LICENSE
cryptoprice_blockxai-0.1.1.dist-info/METADATA
cryptoprice_blockxai-0.1.1.dist-info/WHEEL
cryptoprice_blockxai-0.1.1.dist-info/top_level.txt
cryptoprice_blockxai-0.1.1.dist-info/RECORD
