Metadata-Version: 2.4
Name: cryptoprice-blockxai
Version: 0.1.1
Summary: Super-simple crypto price SDK with caching and retries (Alpha Vantage wrapper)
Author-email: Your Name <you@example.com>
License-Expression: MIT
Project-URL: Homepage, https://github.com/yourname/cryptoprice
Project-URL: Issues, https://github.com/yourname/cryptoprice/issues
Requires-Python: >=3.9
License-File: LICENSE
Requires-Dist: httpx>=0.27.0
Provides-Extra: dev
Requires-Dist: pytest>=8; extra == "dev"
Requires-Dist: respx>=0.21; extra == "dev"
Dynamic: license-file
